near_calculator/__init__.py
near_calculator/near_calculator.py
near_calculator-2.6.1.dist-info/LICENSE.txt
near_calculator-2.6.1.dist-info/METADATA
near_calculator-2.6.1.dist-info/WHEEL
near_calculator-2.6.1.dist-info/top_level.txt
near_calculator-2.6.1.dist-info/RECORD
