Metadata-Version: 2.1
Name: near-calculator
Version: 2.6.1
Author: Caique Santos Carvalho
Author-email: subdr2nk@gmail.com
License: LICENSE.txt
Requires-Python: >=3.7.6
License-File: LICENSE.txt
Requires-Dist: setuptools >=40.4.0
